{
  "last_node_id": 82,
  "last_link_id": 222,
  "nodes": [
    {
      "id": 16,
      "type": "KSamplerSelect",
      "pos": [
        484,
        751
      ],
      "size": [
        315,
        58
      ],
      "flags": {},
      "order": 0,
      "mode": 0,
      "inputs": [],
      "outputs": [
        {
          "name": "SAMPLER",
          "type": "SAMPLER",
          "shape": 3,
          "links": [
            19
          ]
        }
      ],
      "properties": {
        "cnr_id": "comfy-core",
        "ver": "0.3.24",
        "Node name for S&R": "KSamplerSelect"
      },
      "widgets_values": [
        "euler"
      ]
    },
    {
      "id": 22,
      "type": "BasicGuider",
      "pos": [
        600,
        0
      ],
      "size": [
        222.3482666015625,
        46
      ],
      "flags": {},
      "order": 11,
      "mode": 0,
      "inputs": [
        {
          "name": "model",
          "type": "MODEL",
          "link": 195,
          "slot_index": 0
        },
        {
          "name": "conditioning",
          "type": "CONDITIONING",
          "link": 129,
          "slot_index": 1
        }
      ],
      "outputs": [
        {
          "name": "GUIDER",
          "type": "GUIDER",
          "shape": 3,
          "links": [
            30
          ],
          "slot_index": 0
        }
      ],
      "properties": {
        "cnr_id": "comfy-core",
        "ver": "0.3.24",
        "Node name for S&R": "BasicGuider"
      },
      "widgets_values": []
    },
    {
      "id": 8,
      "type": "VAEDecode",
      "pos": [
        1150,
        90
      ],
      "size": [
        210,
        46
      ],
      "flags": {},
      "order": 13,
      "mode": 2,
      "inputs": [
        {
          "name": "samples",
          "type": "LATENT",
          "link": 181
        },
        {
          "name": "vae",
          "type": "VAE",
          "link": 206
        }
      ],
      "outputs": [
        {
          "name": "IMAGE",
          "type": "IMAGE",
          "links": [],
          "slot_index": 0
        }
      ],
      "properties": {
        "cnr_id": "comfy-core",
        "ver": "0.3.24",
        "Node name for S&R": "VAEDecode"
      },
      "widgets_values": []
    },
    {
      "id": 13,
      "type": "SamplerCustomAdvanced",
      "pos": [
        860,
        200
      ],
      "size": [
        272.3617858886719,
        124.53733825683594
      ],
      "flags": {},
      "order": 12,
      "mode": 0,
      "inputs": [
        {
          "name": "noise",
          "type": "NOISE",
          "link": 37,
          "slot_index": 0
        },
        {
          "name": "guider",
          "type": "GUIDER",
          "link": 30,
          "slot_index": 1
        },
        {
          "name": "sampler",
          "type": "SAMPLER",
          "link": 19,
          "slot_index": 2
        },
        {
          "name": "sigmas",
          "type": "SIGMAS",
          "link": 20,
          "slot_index": 3
        },
        {
          "name": "latent_image",
          "type": "LATENT",
          "link": 180,
          "slot_index": 4
        }
      ],
      "outputs": [
        {
          "name": "output",
          "type": "LATENT",
          "shape": 3,
          "links": [
            181,
            210
          ],
          "slot_index": 0
        },
        {
          "name": "denoised_output",
          "type": "LATENT",
          "shape": 3,
          "links": null
        }
      ],
      "properties": {
        "cnr_id": "comfy-core",
        "ver": "0.3.24",
        "Node name for S&R": "SamplerCustomAdvanced"
      },
      "widgets_values": []
    },
    {
      "id": 25,
      "type": "RandomNoise",
      "pos": [
        479,
        618
      ],
      "size": [
        315,
        82
      ],
      "flags": {},
      "order": 1,
      "mode": 0,
      "inputs": [],
      "outputs": [
        {
          "name": "NOISE",
          "type": "NOISE",
          "shape": 3,
          "links": [
            37
          ]
        }
      ],
      "properties": {
        "cnr_id": "comfy-core",
        "ver": "0.3.24",
        "Node name for S&R": "RandomNoise"
      },
      "widgets_values": [
        929937783361831,
        "randomize"
      ],
      "color": "#2a363b",
      "bgcolor": "#3f5159"
    },
    {
      "id": 73,
      "type": "VAEDecodeTiled",
      "pos": [
        1150,
        200
      ],
      "size": [
        210,
        150
      ],
      "flags": {},
      "order": 14,
      "mode": 0,
      "inputs": [
        {
          "name": "samples",
          "type": "LATENT",
          "link": 210
        },
        {
          "name": "vae",
          "type": "VAE",
          "link": 211
        }
      ],
      "outputs": [
        {
          "name": "IMAGE",
          "type": "IMAGE",
          "links": [
            216
          ],
          "slot_index": 0
        }
      ],
      "properties": {
        "cnr_id": "comfy-core",
        "ver": "0.3.24",
        "Node name for S&R": "VAEDecodeTiled"
      },
      "widgets_values": [
        128,
        32,
        32,
        4
      ]
    },
    {
      "id": 67,
      "type": "ModelSamplingSD3",
      "pos": [
        360,
        0
      ],
      "size": [
        210,
        58
      ],
      "flags": {},
      "order": 10,
      "mode": 0,
      "inputs": [
        {
          "name": "model",
          "type": "MODEL",
          "link": 222
        }
      ],
      "outputs": [
        {
          "name": "MODEL",
          "type": "MODEL",
          "links": [
            195
          ],
          "slot_index": 0
        }
      ],
      "properties": {
        "cnr_id": "comfy-core",
        "ver": "0.3.24",
        "Node name for S&R": "ModelSamplingSD3"
      },
      "widgets_values": [
        17
      ]
    },
    {
      "id": 26,
      "type": "FluxGuidance",
      "pos": [
        520,
        100
      ],
      "size": [
        317.4000244140625,
        58
      ],
      "flags": {},
      "order": 8,
      "mode": 0,
      "inputs": [
        {
          "name": "conditioning",
          "type": "CONDITIONING",
          "link": 175
        }
      ],
      "outputs": [
        {
          "name": "CONDITIONING",
          "type": "CONDITIONING",
          "shape": 3,
          "links": [
            129
          ],
          "slot_index": 0
        }
      ],
      "properties": {
        "cnr_id": "comfy-core",
        "ver": "0.3.24",
        "Node name for S&R": "FluxGuidance"
      },
      "widgets_values": [
        8
      ],
      "color": "#233",
      "bgcolor": "#355"
    },
    {
      "id": 78,
      "type": "VHS_VideoCombine",
      "pos": [
        1445.659912109375,
        185.03477478027344
      ],
      "size": [
        220.3603515625,
        615.1471557617188
      ],
      "flags": {},
      "order": 15,
      "mode": 0,
      "inputs": [
        {
          "name": "images",
          "type": "IMAGE",
          "link": 216
        },
        {
          "name": "audio",
          "type": "AUDIO",
          "shape": 7,
          "link": null
        },
        {
          "name": "meta_batch",
          "type": "VHS_BatchManager",
          "shape": 7,
          "link": null
        },
        {
          "name": "vae",
          "type": "VAE",
          "shape": 7,
          "link": null
        }
      ],
      "outputs": [
        {
          "name": "Filenames",
          "type": "VHS_FILENAMES",
          "links": null
        }
      ],
      "properties": {
        "cnr_id": "comfyui-videohelpersuite",
        "ver": "1.5.9",
        "Node name for S&R": "VHS_VideoCombine"
      },
      "widgets_values": {
        "frame_rate": 24,
        "loop_count": 0,
        "filename_prefix": "AnimateDiff",
        "format": "video/h264-mp4",
        "pix_fmt": "yuv420p",
        "crf": 19,
        "save_metadata": true,
        "trim_to_audio": false,
        "pingpong": false,
        "save_output": true,
        "videopreview": {
          "hidden": false,
          "paused": false,
          "params": {
            "filename": "AnimateDiff_00001.mp4",
            "subfolder": "",
            "type": "output",
            "format": "video/h264-mp4",
            "frame_rate": 24,
            "workflow": "AnimateDiff_00001.png",
            "fullpath": "/Volumes/HIDISC SSD/ComfyUI/output/AnimateDiff_00001.mp4"
          },
          "muted": false
        }
      }
    },
    {
      "id": 44,
      "type": "CLIPTextEncode",
      "pos": [
        420,
        200
      ],
      "size": [
        422.84503173828125,
        164.31304931640625
      ],
      "flags": {},
      "order": 6,
      "mode": 0,
      "inputs": [
        {
          "name": "clip",
          "type": "CLIP",
          "link": 217
        }
      ],
      "outputs": [
        {
          "name": "CONDITIONING",
          "type": "CONDITIONING",
          "links": [
            175
          ],
          "slot_index": 0
        }
      ],
      "title": "CLIP Text Encode (Positive Prompt)",
      "properties": {
        "cnr_id": "comfy-core",
        "ver": "0.3.24",
        "Node name for S&R": "CLIPTextEncode"
      },
      "widgets_values": [
        "This is a high quality realistic movie of a cat walking in bedroom."
      ],
      "color": "#232",
      "bgcolor": "#353"
    },
    {
      "id": 17,
      "type": "BasicScheduler",
      "pos": [
        478,
        860
      ],
      "size": [
        315,
        106
      ],
      "flags": {},
      "order": 9,
      "mode": 0,
      "inputs": [
        {
          "name": "model",
          "type": "MODEL",
          "link": 221,
          "slot_index": 0
        }
      ],
      "outputs": [
        {
          "name": "SIGMAS",
          "type": "SIGMAS",
          "shape": 3,
          "links": [
            20
          ]
        }
      ],
      "properties": {
        "cnr_id": "comfy-core",
        "ver": "0.3.24",
        "Node name for S&R": "BasicScheduler"
      },
      "widgets_values": [
        "simple",
        6,
        1
      ]
    },
    {
      "id": 45,
      "type": "EmptyHunyuanLatentVideo",
      "pos": [
        475.540771484375,
        432.673583984375
      ],
      "size": [
        315,
        130
      ],
      "flags": {},
      "order": 2,
      "mode": 0,
      "inputs": [],
      "outputs": [
        {
          "name": "LATENT",
          "type": "LATENT",
          "links": [
            180
          ],
          "slot_index": 0
        }
      ],
      "properties": {
        "cnr_id": "comfy-core",
        "ver": "0.3.24",
        "Node name for S&R": "EmptyHunyuanLatentVideo"
      },
      "widgets_values": [
        480,
        640,
        25,
        1
      ]
    },
    {
      "id": 10,
      "type": "VAELoader",
      "pos": [
        20,
        292
      ],
      "size": [
        350,
        60
      ],
      "flags": {},
      "order": 3,
      "mode": 0,
      "inputs": [],
      "outputs": [
        {
          "name": "VAE",
          "type": "VAE",
          "shape": 3,
          "links": [
            206,
            211
          ],
          "slot_index": 0
        }
      ],
      "properties": {
        "cnr_id": "comfy-core",
        "ver": "0.3.24",
        "Node name for S&R": "VAELoader"
      },
      "widgets_values": [
        "hunyuan_video_vae_bf16.safetensors"
      ]
    },
    {
      "id": 79,
      "type": "DualCLIPLoaderGGUF",
      "pos": [
        26.62206268310547,
        426.28326416015625
      ],
      "size": [
        315,
        106
      ],
      "flags": {},
      "order": 4,
      "mode": 0,
      "inputs": [],
      "outputs": [
        {
          "name": "CLIP",
          "type": "CLIP",
          "links": [
            217
          ],
          "slot_index": 0
        }
      ],
      "properties": {
        "cnr_id": "comfyui-gguf",
        "ver": "298192ed60f8ca821c6fe5f8030cae23424cada5",
        "Node name for S&R": "DualCLIPLoaderGGUF",
        "aux_id": "city96/ComfyUI-GGUF"
      },
      "widgets_values": [
        "clip_l.safetensors",
        "llava-llama-3-8B-v1_1-Q4_K_M.gguf",
        "hunyuan_video"
      ]
    },
    {
      "id": 80,
      "type": "UnetLoaderGGUF",
      "pos": [
        25.511699676513672,
        605.9157104492188
      ],
      "size": [
        315,
        58
      ],
      "flags": {},
      "order": 5,
      "mode": 0,
      "inputs": [],
      "outputs": [
        {
          "name": "MODEL",
          "type": "MODEL",
          "links": [
            220
          ],
          "slot_index": 0
        }
      ],
      "properties": {
        "cnr_id": "comfyui-gguf",
        "ver": "298192ed60f8ca821c6fe5f8030cae23424cada5",
        "Node name for S&R": "UnetLoaderGGUF",
        "aux_id": "city96/ComfyUI-GGUF"
      },
      "widgets_values": [
        "hunyuan-video-t2v-720p-Q4_K_M.gguf"
      ]
    },
    {
      "id": 82,
      "type": "HunyuanVideoLoraLoader",
      "pos": [
        130.2493438720703,
        861.9112548828125
      ],
      "size": [
        315,
        106
      ],
      "flags": {},
      "order": 7,
      "mode": 0,
      "inputs": [
        {
          "name": "model",
          "type": "MODEL",
          "link": 220
        }
      ],
      "outputs": [
        {
          "name": "model",
          "type": "MODEL",
          "links": [
            221,
            222
          ],
          "slot_index": 0
        }
      ],
      "properties": {
        "aux_id": "facok/ComfyUI-HunyuanVideoMultiLora",
        "ver": "d41fbcb319a84fa6ba8eb10653ff501a9653b639",
        "Node name for S&R": "HunyuanVideoLoraLoader"
      },
      "widgets_values": [
        "hyvideo_FastVideo_LoRA-fp8.safetensors",
        1,
        "all"
      ]
    }
  ],
  "links": [
    [
      19,
      16,
      0,
      13,
      2,
      "SAMPLER"
    ],
    [
      20,
      17,
      0,
      13,
      3,
      "SIGMAS"
    ],
    [
      30,
      22,
      0,
      13,
      1,
      "GUIDER"
    ],
    [
      37,
      25,
      0,
      13,
      0,
      "NOISE"
    ],
    [
      129,
      26,
      0,
      22,
      1,
      "CONDITIONING"
    ],
    [
      175,
      44,
      0,
      26,
      0,
      "CONDITIONING"
    ],
    [
      180,
      45,
      0,
      13,
      4,
      "LATENT"
    ],
    [
      181,
      13,
      0,
      8,
      0,
      "LATENT"
    ],
    [
      195,
      67,
      0,
      22,
      0,
      "MODEL"
    ],
    [
      206,
      10,
      0,
      8,
      1,
      "VAE"
    ],
    [
      210,
      13,
      0,
      73,
      0,
      "LATENT"
    ],
    [
      211,
      10,
      0,
      73,
      1,
      "VAE"
    ],
    [
      216,
      73,
      0,
      78,
      0,
      "IMAGE"
    ],
    [
      217,
      79,
      0,
      44,
      0,
      "CLIP"
    ],
    [
      220,
      80,
      0,
      82,
      0,
      "MODEL"
    ],
    [
      221,
      82,
      0,
      17,
      0,
      "MODEL"
    ],
    [
      222,
      82,
      0,
      67,
      0,
      "MODEL"
    ]
  ],
  "groups": [],
  "config": {},
  "extra": {
    "ds": {
      "scale": 0.620921323059155,
      "offset": [
        271.1824394815945,
        193.35398594289978
      ]
    },
    "groupNodes": {},
    "node_versions": {
      "comfy-core": "v0.3.10-25-g0b9839e",
      "ComfyUI-GGUF": "3dc384b23366983b28222cbf681b808053949a43"
    },
    "VHS_latentpreview": false,
    "VHS_latentpreviewrate": 0,
    "VHS_MetadataImage": true,
    "VHS_KeepIntermediate": true
  },
  "version": 0.4
}